woofy/__init__.py
woofy/client.py
woofy/manager/__init__.py
woofy/manager/image.py
woofy/py.typed
woofy/struct/__init__.py
woofy/struct/image.py
woofy-1.0.1.dist-info/LICENSE
woofy-1.0.1.dist-info/METADATA
woofy-1.0.1.dist-info/WHEEL
woofy-1.0.1.dist-info/RECORD
